{
  "name" : "D - Deforestation",
  "testType" : "SINGLE",
  "input" : {
    "type" : "STANDARD",
    "fileName" : "input.txt"
  },
  "output" : {
    "type" : "STANDARD",
    "fileName" : "output.txt"
  },
  "tests" : [ {
    "input" : "4 2\n2 1 2\n5 2 3",
    "output" : "12\n",
    "index" : 0,
    "active" : true
  }, {
    "input" : "10 5\n8 1 4\n11 6 7\n20 1 1\n31 9 9\n36 1 1",
    "output" : "113",
    "index" : 1,
    "active" : true
  }, {
    "input" : "10 10\n76724435 3 4\n118633459 1 2\n288866156 6 9\n470883673 6 10\n521545097 2 4\n827053186 1 1\n856004743 2 4\n873331881 1 1\n909855542 6 10\n916091889 8 9",
    "output" : "8003096514",
    "index" : 2,
    "active" : true
  } ],
  "location" : "src/jp/llv/atcoder",
  "vmArgs" : "-Xmx1024M",
  "mainClass" : "Main",
  "taskClass" : "jp.llv.atcoder.DDeforestation",
  "checkerClass" : "net.egork.chelper.checkers.TokenChecker",
  "checkerParameters" : "",
  "testClasses" : [ ],
  "date" : "2019.02.17",
  "contestName" : "全国統一プログラミング王決定戦本戦",
  "truncate" : true,
  "inputClass" : "jp.llv.atcoder.lib.io.LightScanner",
  "outputClass" : "jp.llv.atcoder.lib.io.LightWriter",
  "includeLocale" : false,
  "failOnOverflow" : false,
  "interactive" : false,
  "interactor" : "net.egork.chelper.tester.Interactor"
}